termsite/__init__.py
termsite/__main__.py
termsite/onfire.py
onfire-0.1.1.dist-info/METADATA
onfire-0.1.1.dist-info/WHEEL
onfire-0.1.1.dist-info/entry_points.txt
onfire-0.1.1.dist-info/RECORD
