Metadata-Version: 2.4
Name: onfire
Version: 0.1.1
Summary: AAFire-style terminal fire in pure Python + curses.
Author: Code
License: MIT
Keywords: aafire,ascii,curses,fire,terminal
Classifier: Environment :: Console :: Curses
Classifier: License :: OSI Approved :: MIT License
Classifier: Programming Language :: Python :: 3
Classifier: Programming Language :: Python :: 3 :: Only
Classifier: Topic :: Artistic Software
Classifier: Topic :: Games/Entertainment
Requires-Python: >=3.10
Requires-Dist: psutil>=7.2.1
Provides-Extra: windows
Requires-Dist: windows-curses>=2.3.2; extra == 'windows'
